dfhelper/__init__.py
dfhelper/scout.py
dfhelper/viz.py
dfhelper/package_utils/__init__.py
dfhelper/package_utils/utils_assert.py
dfhelper/package_utils/utils_transform_df.py
dfhelper-0.0.6.dist-info/METADATA
dfhelper-0.0.6.dist-info/WHEEL
dfhelper-0.0.6.dist-info/top_level.txt
dfhelper-0.0.6.dist-info/RECORD
