Metadata-Version: 2.1
Name: dfhelper
Version: 0.0.6
Summary: dfhelper is a Python package that simplifies data preprocessing and visualization in Jupyter Notebooks.
Home-page: https://github.com/kodurd/dfhelper
Author: kodurd
Author-email: koldunov.eduard1@gmail.com
Project-URL: GitHub, https://github.com/kodurd/dfhelper
Keywords: preprocessing visualization
Classifier: Programming Language :: Python :: 3.11
Classifier: License :: OSI Approved :: MIT License
Classifier: Operating System :: OS Independent
Requires-Python: >=3.9
Requires-Dist: pandas
Requires-Dist: ipython
